setup.py
openwrt/__init__.py
openwrt/backup.py
openwrt/dhcp.py
openwrt/manager.py
openwrt/portforwarding.py
openwrt/services.py
openwrt/users.py
openwrt/core/__init__.py
openwrt/core/rpcproxy.py
openwrt/core/shell.py
openwrt/network/__init__.py
openwrt/network/dhcpprofile.py
openwrt/network/manager.py
openwrt/network/profile.py
openwrt/network/staticprofile.py
openwrt/network/util.py
openwrt_remote_manager.egg-info/PKG-INFO
openwrt_remote_manager.egg-info/SOURCES.txt
openwrt_remote_manager.egg-info/dependency_links.txt
openwrt_remote_manager.egg-info/top_level.txt