Metadata-Version: 1.0
Name: openwrt-remote-manager
Version: 1.3
Summary: A Python module for remotely managing an OpenWRT instance
Home-page: https://github.com/Jumpscale/openwrt-remote-manager
Author: Amr Hassan
Author-email: amr.hassan@gmail.com
License: UNKNOWN
Platform: UNKNOWN
